mcp_server_motherduck/__init__.py
mcp_server_motherduck/configs.py
mcp_server_motherduck/database.py
mcp_server_motherduck/prompt.py
mcp_server_motherduck/server.py
mcp_server_motherduck_fastmcp-0.8.1.dist-info/METADATA
mcp_server_motherduck_fastmcp-0.8.1.dist-info/WHEEL
mcp_server_motherduck_fastmcp-0.8.1.dist-info/entry_points.txt
mcp_server_motherduck_fastmcp-0.8.1.dist-info/licenses/LICENSE
mcp_server_motherduck_fastmcp-0.8.1.dist-info/RECORD
