Metadata-Version: 2.4
Name: mcp-server-motherduck-fastmcp
Version: 0.8.1
Summary: A MCP server for MotherDuck and local DuckDB
Project-URL: Homepage, https://github.com/fastmcp-me/mcp-server-motherduck#readme
Project-URL: Repository, https://github.com/fastmcp-me/mcp-server-motherduck.git
Project-URL: Issues, https://github.com/fastmcp-me/mcp-server-motherduck/issues
Author-email: tdoehmen <till@motherduck.com>
License-File: LICENSE
Requires-Python: >=3.10
Requires-Dist: anyio>=4.8.0
Requires-Dist: click>=8.1.8
Requires-Dist: duckdb==1.4.1
Requires-Dist: mcp>=1.9.4
Requires-Dist: pytz>=2025.2
Requires-Dist: starlette>=0.46.1
Requires-Dist: tabulate>=0.9.0
Requires-Dist: uvicorn>=0.34.0
